confmg/__init__.py
confmg/__main__.py
confmg-1.0.0.dist-info/METADATA
confmg-1.0.0.dist-info/WHEEL
confmg-1.0.0.dist-info/entry_points.txt
confmg-1.0.0.dist-info/top_level.txt
confmg-1.0.0.dist-info/RECORD
